data/__init__.py
data/web_scraper.py
data/io/__init__.py
data/io/loader.py
data/io/writer.py
data/miner/__init__.py
model/__init__.py
superstocks-0.0.1.dist-info/LICENSE
superstocks-0.0.1.dist-info/METADATA
superstocks-0.0.1.dist-info/WHEEL
superstocks-0.0.1.dist-info/top_level.txt
superstocks-0.0.1.dist-info/RECORD
