Metadata-Version: 2.1
Name: superstocks
Version: 0.0.1
Summary: Unified AI trading platform powered by human intelligence.
Home-page: UNKNOWN
Author: Kumar Nityan Suman
Author-email: nityan.suman@gmail.com
License: UNKNOWN
Platform: UNKNOWN
Classifier: Programming Language :: Python :: 3
Classifier: Operating System :: OS Independent
Requires-Python: >=3.8
License-File: LICENSE
